lib_travis/__init__.py
lib_travis/__init__conf__.py
lib_travis/lib_travis.py
lib_travis/lib_travis_cli.py
lib_travis/py.typed
lib_travis-2.3.12.dist-info/LICENSE
lib_travis-2.3.12.dist-info/METADATA
lib_travis-2.3.12.dist-info/WHEEL
lib_travis-2.3.12.dist-info/entry_points.txt
lib_travis-2.3.12.dist-info/top_level.txt
lib_travis-2.3.12.dist-info/RECORD
