Metadata-Version: 2.1
Name: lib-travis
Version: 2.3.12
Summary: travis related utilities
Home-page: https://github.com/bitranox/lib_travis
Author: Robert Nowotny
Author-email: bitranox@gmail.com
License: UNKNOWN
Platform: UNKNOWN
Classifier: Development Status :: 5 - Production/Stable
Classifier: Intended Audience :: Developers
Classifier: License :: OSI Approved :: MIT License
Classifier: Natural Language :: English
Classifier: Operating System :: OS Independent
Classifier: Programming Language :: Python
Classifier: Topic :: Software Development :: Libraries :: Python Modules
Requires-Python: >=3.6.0
Requires-Dist: click
Requires-Dist: cli-exit-tools
Requires-Dist: lib-log-utils
Requires-Dist: rst-include
